oldp/__init__.py
oldp/settings.py
oldp/urls.py
oldp/wsgi.py
oldp/api/__init__.py
oldp/api/signals.py
oldp/api/views.py
oldp/api/tests/__init__.py
oldp/api/tests/test_views.py
oldp/apps/__init__.py
oldp/apps/accounts/__init__.py
oldp/apps/accounts/apps.py
oldp/apps/accounts/urls.py
oldp/apps/accounts/views.py
oldp/apps/accounts/tests/__init__.py
oldp/apps/accounts/tests/test_views.py
oldp/apps/backend/__init__.py
oldp/apps/backend/admin.py
oldp/apps/backend/apps.py
oldp/apps/backend/models.py
oldp/apps/backend/views.py
oldp/apps/backend/management/__init__.py
oldp/apps/backend/management/commands/__init__.py
oldp/apps/backend/management/commands/generate_related.py
oldp/apps/backend/migrations/__init__.py
oldp/apps/backend/processing/__init__.py
oldp/apps/backend/processing/content_processor.py
oldp/apps/backend/processing/processing_steps/__init__.py
oldp/apps/backend/processing/processing_steps/post/__init__.py
oldp/apps/backend/processing/processing_steps/post/send_to_es.py
oldp/apps/backend/processing/processing_steps/post/send_to_fs.py
oldp/apps/cases/__init__.py
oldp/apps/cases/admin.py
oldp/apps/cases/apps.py
oldp/apps/cases/models.py
oldp/apps/cases/serializers.py
oldp/apps/cases/urls.py
oldp/apps/cases/views.py
oldp/apps/cases/management/__init__.py
oldp/apps/cases/management/commands/__init__.py
oldp/apps/cases/management/commands/assign_topics.py
oldp/apps/cases/management/commands/process_cases.py
oldp/apps/cases/migrations/0001_initial.py
oldp/apps/cases/migrations/0002_auto_20171221_1055.py
oldp/apps/cases/migrations/0003_auto_20180209_0926.py
oldp/apps/cases/migrations/0004_auto_20180209_1748.py
oldp/apps/cases/migrations/0005_auto_20180424_0849.py
oldp/apps/cases/migrations/0006_auto_20180425_0726.py
oldp/apps/cases/migrations/0007_auto_20180425_2039.py
oldp/apps/cases/migrations/0008_auto_20180426_0806.py
oldp/apps/cases/migrations/0009_auto_20180430_1225.py
oldp/apps/cases/migrations/__init__.py
oldp-0.0.1.dist-info/METADATA
oldp-0.0.1.dist-info/RECORD
oldp-0.0.1.dist-info/WHEEL
oldp-0.0.1.dist-info/top_level.txt
