Metadata-Version: 2.1
Name: oldp
Version: 0.0.1
Summary: Open Legal Data Platform
Home-page: https://github.com/openlegaldata/oldp
Author: Malte Schwarzer
Author-email: hello@openlegaldata.io
License: MIT
Platform: UNKNOWN
Classifier: Development Status :: 5 - Production/Stable
Classifier: Framework :: Django
Classifier: Intended Audience :: Developers
Classifier: License :: OSI Approved :: MIT License
Classifier: Operating System :: OS Independent
Classifier: Programming Language :: Python
Classifier: Programming Language :: Python :: 3.5
Classifier: Topic :: Utilities
Requires-Dist: cssselect
Requires-Dist: dj-database-url
Requires-Dist: Django
Requires-Dist: django-appconf
Requires-Dist: django-compressor
Requires-Dist: django-configurations
Requires-Dist: django-filter
Requires-Dist: django-mathfilters
Requires-Dist: django-sass-processor
Requires-Dist: django-stronghold
Requires-Dist: django-tellme
Requires-Dist: django-widget-tweaks
Requires-Dist: djangorestframework
Requires-Dist: elasticsearch
Requires-Dist: elasticsearch-dsl
Requires-Dist: gunicorn
Requires-Dist: isodate
Requires-Dist: libsass
Requires-Dist: lxml
Requires-Dist: Markdown
Requires-Dist: mysqlclient
Requires-Dist: nltk
Requires-Dist: pdfminer.six
Requires-Dist: Pillow
Requires-Dist: pycryptodome
Requires-Dist: pypandoc
Requires-Dist: python-dateutil
Requires-Dist: requests
Requires-Dist: requests-toolbelt
Requires-Dist: six
Requires-Dist: SOAPpy
Requires-Dist: stem
Requires-Dist: urllib3
Requires-Dist: whitenoise
Requires-Dist: wstools
Requires-Dist: zeep
